{
    "last_verified":  "2026-04-18T15:59:17.6848036+02:00",
    "suite_version":  "1.15.0",
    "files":  {
                  "kata/SKILL.md":  "87412A46A4F87A8B",
                  "kaizen/SKILL.md":  "462EAE71A23F8B37",
                  "kaikaku/SKILL.md":  "83D20EF3B42C6AA2",
                  "mura/SKILL.md":  "74CDD4263BF1CB55",
                  "muri/SKILL.md":  "038524AE9C12E884",
                  "muda/SKILL.md":  "6EA090D896C33F5E",
                  "hansei/SKILL.md":  "EE4DE7CC4CFF7192",
                  "GENBA.md":  "30C9CD624220989B",
                  "SCORECARD.md":  "FB591C583786A4A3",
                  "CHANGELOG.md":  "0B4B5B553A698903",
                  "PRINCIPLES.md":  "E5152D6BDC751BDE"
              }
}
